elenchos_check_memory/CheckMemoryCommand.py
elenchos_check_memory/MemoryPlugin.py
elenchos_check_memory/__init__.py
elenchos_check_memory/commands.xml
elenchos_check_memory-0.2.0.dist-info/LICENSE.md
elenchos_check_memory-0.2.0.dist-info/METADATA
elenchos_check_memory-0.2.0.dist-info/WHEEL
elenchos_check_memory-0.2.0.dist-info/RECORD
